{
  "run_timestamp_utc": "2026-07-19T14:21:35Z",
  "anchor_timestamp_utc": "2026-07-19T14:00:00Z",
  "model": {
    "profile": "in12h_out12h_gnn_patchtst",
    "checkpoint_path": "checkpoint/model_best.pth",
    "checkpoint_sha256": "6625c0b04d36",
    "val_loss_at_train": null,
    "val_mae_at_train": null,
    "val_rmse_at_train": null
  },
  "input": {
    "event_csv": "/home/runner/work/hp-prediction/hp-prediction/vendor/realtime-regression-sw/dataset/events/20260719140000.csv",
    "sources": {
      "noaa_plasma_url": "https://services.swpc.noaa.gov/json/rtsw/rtsw_wind_1m.json",
      "noaa_mag_url": "https://services.swpc.noaa.gov/json/rtsw/rtsw_mag_1m.json",
      "gfz_hpo_url": "https://www-app3.gfz-potsdam.de/kp_index/Hp30_ap30_nowcast.txt"
    },
    "missing_data_filled_fraction": 0.003623
  },
  "forecast": [
    {
      "horizon_steps": 1,
      "horizon_minutes": 30,
      "target_timestamp_utc": "2026-07-19T14:30:00Z",
      "hp30": 0.8879227042198181
    },
    {
      "horizon_steps": 2,
      "horizon_minutes": 60,
      "target_timestamp_utc": "2026-07-19T15:00:00Z",
      "hp30": 0.9855480194091797
    },
    {
      "horizon_steps": 3,
      "horizon_minutes": 90,
      "target_timestamp_utc": "2026-07-19T15:30:00Z",
      "hp30": 1.0514839887619019
    },
    {
      "horizon_steps": 4,
      "horizon_minutes": 120,
      "target_timestamp_utc": "2026-07-19T16:00:00Z",
      "hp30": 1.1216380596160889
    },
    {
      "horizon_steps": 5,
      "horizon_minutes": 150,
      "target_timestamp_utc": "2026-07-19T16:30:00Z",
      "hp30": 1.1875900030136108
    },
    {
      "horizon_steps": 6,
      "horizon_minutes": 180,
      "target_timestamp_utc": "2026-07-19T17:00:00Z",
      "hp30": 1.2984932661056519
    },
    {
      "horizon_steps": 7,
      "horizon_minutes": 210,
      "target_timestamp_utc": "2026-07-19T17:30:00Z",
      "hp30": 1.1759753227233887
    },
    {
      "horizon_steps": 8,
      "horizon_minutes": 240,
      "target_timestamp_utc": "2026-07-19T18:00:00Z",
      "hp30": 1.2951874732971191
    },
    {
      "horizon_steps": 9,
      "horizon_minutes": 270,
      "target_timestamp_utc": "2026-07-19T18:30:00Z",
      "hp30": 1.2676775455474854
    },
    {
      "horizon_steps": 10,
      "horizon_minutes": 300,
      "target_timestamp_utc": "2026-07-19T19:00:00Z",
      "hp30": 1.3682732582092285
    },
    {
      "horizon_steps": 11,
      "horizon_minutes": 330,
      "target_timestamp_utc": "2026-07-19T19:30:00Z",
      "hp30": 1.4081659317016602
    },
    {
      "horizon_steps": 12,
      "horizon_minutes": 360,
      "target_timestamp_utc": "2026-07-19T20:00:00Z",
      "hp30": 1.5277187824249268
    },
    {
      "horizon_steps": 13,
      "horizon_minutes": 390,
      "target_timestamp_utc": "2026-07-19T20:30:00Z",
      "hp30": 1.4836156368255615
    },
    {
      "horizon_steps": 14,
      "horizon_minutes": 420,
      "target_timestamp_utc": "2026-07-19T21:00:00Z",
      "hp30": 1.539875864982605
    },
    {
      "horizon_steps": 15,
      "horizon_minutes": 450,
      "target_timestamp_utc": "2026-07-19T21:30:00Z",
      "hp30": 1.5360229015350342
    },
    {
      "horizon_steps": 16,
      "horizon_minutes": 480,
      "target_timestamp_utc": "2026-07-19T22:00:00Z",
      "hp30": 1.5758514404296875
    },
    {
      "horizon_steps": 17,
      "horizon_minutes": 510,
      "target_timestamp_utc": "2026-07-19T22:30:00Z",
      "hp30": 1.4855018854141235
    },
    {
      "horizon_steps": 18,
      "horizon_minutes": 540,
      "target_timestamp_utc": "2026-07-19T23:00:00Z",
      "hp30": 1.568149447441101
    },
    {
      "horizon_steps": 19,
      "horizon_minutes": 570,
      "target_timestamp_utc": "2026-07-19T23:30:00Z",
      "hp30": 1.525151252746582
    },
    {
      "horizon_steps": 20,
      "horizon_minutes": 600,
      "target_timestamp_utc": "2026-07-20T00:00:00Z",
      "hp30": 1.5837883949279785
    },
    {
      "horizon_steps": 21,
      "horizon_minutes": 630,
      "target_timestamp_utc": "2026-07-20T00:30:00Z",
      "hp30": 1.6738389730453491
    },
    {
      "horizon_steps": 22,
      "horizon_minutes": 660,
      "target_timestamp_utc": "2026-07-20T01:00:00Z",
      "hp30": 1.5232807397842407
    },
    {
      "horizon_steps": 23,
      "horizon_minutes": 690,
      "target_timestamp_utc": "2026-07-20T01:30:00Z",
      "hp30": 1.6632277965545654
    },
    {
      "horizon_steps": 24,
      "horizon_minutes": 720,
      "target_timestamp_utc": "2026-07-20T02:00:00Z",
      "hp30": 1.5800381898880005
    }
  ],
  "analysis": {
    "mcd": {
      "num_samples": 100,
      "n_std": 2.0,
      "mean": [
        0.9279520511627197,
        1.0464980602264404,
        1.0936980247497559,
        1.182176113128662,
        1.2346442937850952,
        1.3421400785446167,
        1.223160743713379,
        1.348373532295227,
        1.3323380947113037,
        1.4449267387390137,
        1.4431779384613037,
        1.5643317699432373,
        1.5059046745300293,
        1.5837631225585938,
        1.573625087738037,
        1.6266059875488281,
        1.534319281578064,
        1.6055572032928467,
        1.5888068675994873,
        1.622426152229309,
        1.7360877990722656,
        1.594301700592041,
        1.6998523473739624,
        1.6116108894348145
      ],
      "std": [
        0.15119042992591858,
        0.1545332670211792,
        0.1628796011209488,
        0.1847035139799118,
        0.1734577864408493,
        0.207582488656044,
        0.18148721754550934,
        0.2095862329006195,
        0.20171083509922028,
        0.22036568820476532,
        0.2143835574388504,
        0.23999977111816406,
        0.1994112879037857,
        0.2589261829853058,
        0.20417152345180511,
        0.26050323247909546,
        0.24416737258434296,
        0.2565279006958008,
        0.24549952149391174,
        0.26808780431747437,
        0.2903062105178833,
        0.2704756259918213,
        0.24364551901817322,
        0.23817425966262817
      ],
      "lower": [
        0.6255711913108826,
        0.737431526184082,
        0.7679388523101807,
        0.8127690553665161,
        0.8877286911010742,
        0.9269751310348511,
        0.8601863384246826,
        0.929201066493988,
        0.9289164543151855,
        1.0041953325271606,
        1.0144108533859253,
        1.0843322277069092,
        1.1070821285247803,
        1.065910816192627,
        1.1652820110321045,
        1.1055995225906372,
        1.0459845066070557,
        1.0925014019012451,
        1.0978078842163086,
        1.0862505435943604,
        1.155475378036499,
        1.0533504486083984,
        1.2125613689422607,
        1.135262370109558
      ],
      "upper": [
        1.230332851409912,
        1.3555645942687988,
        1.419457197189331,
        1.551583170890808,
        1.5815598964691162,
        1.7573050260543823,
        1.5861351490020752,
        1.7675459384918213,
        1.7357597351074219,
        1.8856581449508667,
        1.8719450235366821,
        2.0443313121795654,
        1.9047272205352783,
        2.1016154289245605,
        1.9819681644439697,
        2.1476125717163086,
        2.0226540565490723,
        2.1186130046844482,
        2.079805850982666,
        2.158601760864258,
        2.3167002201080322,
        2.1352529525756836,
        2.187143325805664,
        2.0879592895507812
      ]
    }
  },
  "history": [
    {
      "timestamp_utc": "2026-07-19T02:30:00Z",
      "hp30": 0.333
    },
    {
      "timestamp_utc": "2026-07-19T03:00:00Z",
      "hp30": 0.0
    },
    {
      "timestamp_utc": "2026-07-19T03:30:00Z",
      "hp30": 0.0
    },
    {
      "timestamp_utc": "2026-07-19T04:00:00Z",
      "hp30": 0.667
    },
    {
      "timestamp_utc": "2026-07-19T04:30:00Z",
      "hp30": 1.0
    },
    {
      "timestamp_utc": "2026-07-19T05:00:00Z",
      "hp30": 0.667
    },
    {
      "timestamp_utc": "2026-07-19T05:30:00Z",
      "hp30": 1.333
    },
    {
      "timestamp_utc": "2026-07-19T06:00:00Z",
      "hp30": 1.333
    },
    {
      "timestamp_utc": "2026-07-19T06:30:00Z",
      "hp30": 0.667
    },
    {
      "timestamp_utc": "2026-07-19T07:00:00Z",
      "hp30": 0.667
    },
    {
      "timestamp_utc": "2026-07-19T07:30:00Z",
      "hp30": 0.667
    },
    {
      "timestamp_utc": "2026-07-19T08:00:00Z",
      "hp30": 0.667
    },
    {
      "timestamp_utc": "2026-07-19T08:30:00Z",
      "hp30": 0.667
    },
    {
      "timestamp_utc": "2026-07-19T09:00:00Z",
      "hp30": 0.333
    },
    {
      "timestamp_utc": "2026-07-19T09:30:00Z",
      "hp30": 0.667
    },
    {
      "timestamp_utc": "2026-07-19T10:00:00Z",
      "hp30": 0.333
    },
    {
      "timestamp_utc": "2026-07-19T10:30:00Z",
      "hp30": 0.333
    },
    {
      "timestamp_utc": "2026-07-19T11:00:00Z",
      "hp30": 0.333
    },
    {
      "timestamp_utc": "2026-07-19T11:30:00Z",
      "hp30": 0.333
    },
    {
      "timestamp_utc": "2026-07-19T12:00:00Z",
      "hp30": 0.333
    },
    {
      "timestamp_utc": "2026-07-19T12:30:00Z",
      "hp30": 0.667
    },
    {
      "timestamp_utc": "2026-07-19T13:00:00Z",
      "hp30": 0.333
    },
    {
      "timestamp_utc": "2026-07-19T13:30:00Z",
      "hp30": 0.667
    },
    {
      "timestamp_utc": "2026-07-19T14:00:00Z",
      "hp30": 0.667
    }
  ]
}