{
  "run_timestamp_utc": "2026-07-14T07:33:18Z",
  "anchor_timestamp_utc": "2026-07-14T07:30:00Z",
  "model": {
    "profile": "in12h_out12h_gnn_patchtst",
    "checkpoint_path": "checkpoint/model_best.pth",
    "checkpoint_sha256": "6625c0b04d36",
    "val_loss_at_train": null,
    "val_mae_at_train": null,
    "val_rmse_at_train": null
  },
  "input": {
    "event_csv": "/home/runner/work/hp-prediction/hp-prediction/vendor/realtime-regression-sw/dataset/events/20260714073000.csv",
    "sources": {
      "noaa_plasma_url": "https://services.swpc.noaa.gov/json/rtsw/rtsw_wind_1m.json",
      "noaa_mag_url": "https://services.swpc.noaa.gov/json/rtsw/rtsw_mag_1m.json",
      "gfz_hpo_url": "https://www-app3.gfz-potsdam.de/kp_index/Hp30_ap30_nowcast.txt"
    },
    "missing_data_filled_fraction": 0.04529
  },
  "forecast": [
    {
      "horizon_steps": 1,
      "horizon_minutes": 30,
      "target_timestamp_utc": "2026-07-14T08:00:00Z",
      "hp30": 1.6947131156921387
    },
    {
      "horizon_steps": 2,
      "horizon_minutes": 60,
      "target_timestamp_utc": "2026-07-14T08:30:00Z",
      "hp30": 1.6527190208435059
    },
    {
      "horizon_steps": 3,
      "horizon_minutes": 90,
      "target_timestamp_utc": "2026-07-14T09:00:00Z",
      "hp30": 1.733748197555542
    },
    {
      "horizon_steps": 4,
      "horizon_minutes": 120,
      "target_timestamp_utc": "2026-07-14T09:30:00Z",
      "hp30": 1.6451070308685303
    },
    {
      "horizon_steps": 5,
      "horizon_minutes": 150,
      "target_timestamp_utc": "2026-07-14T10:00:00Z",
      "hp30": 1.7613452672958374
    },
    {
      "horizon_steps": 6,
      "horizon_minutes": 180,
      "target_timestamp_utc": "2026-07-14T10:30:00Z",
      "hp30": 1.7084910869598389
    },
    {
      "horizon_steps": 7,
      "horizon_minutes": 210,
      "target_timestamp_utc": "2026-07-14T11:00:00Z",
      "hp30": 1.745577096939087
    },
    {
      "horizon_steps": 8,
      "horizon_minutes": 240,
      "target_timestamp_utc": "2026-07-14T11:30:00Z",
      "hp30": 1.7078521251678467
    },
    {
      "horizon_steps": 9,
      "horizon_minutes": 270,
      "target_timestamp_utc": "2026-07-14T12:00:00Z",
      "hp30": 1.707970142364502
    },
    {
      "horizon_steps": 10,
      "horizon_minutes": 300,
      "target_timestamp_utc": "2026-07-14T12:30:00Z",
      "hp30": 1.7641535997390747
    },
    {
      "horizon_steps": 11,
      "horizon_minutes": 330,
      "target_timestamp_utc": "2026-07-14T13:00:00Z",
      "hp30": 1.775410532951355
    },
    {
      "horizon_steps": 12,
      "horizon_minutes": 360,
      "target_timestamp_utc": "2026-07-14T13:30:00Z",
      "hp30": 1.8163316249847412
    },
    {
      "horizon_steps": 13,
      "horizon_minutes": 390,
      "target_timestamp_utc": "2026-07-14T14:00:00Z",
      "hp30": 1.8429350852966309
    },
    {
      "horizon_steps": 14,
      "horizon_minutes": 420,
      "target_timestamp_utc": "2026-07-14T14:30:00Z",
      "hp30": 1.8306750059127808
    },
    {
      "horizon_steps": 15,
      "horizon_minutes": 450,
      "target_timestamp_utc": "2026-07-14T15:00:00Z",
      "hp30": 1.8636740446090698
    },
    {
      "horizon_steps": 16,
      "horizon_minutes": 480,
      "target_timestamp_utc": "2026-07-14T15:30:00Z",
      "hp30": 1.8102004528045654
    },
    {
      "horizon_steps": 17,
      "horizon_minutes": 510,
      "target_timestamp_utc": "2026-07-14T16:00:00Z",
      "hp30": 1.835558295249939
    },
    {
      "horizon_steps": 18,
      "horizon_minutes": 540,
      "target_timestamp_utc": "2026-07-14T16:30:00Z",
      "hp30": 1.8784146308898926
    },
    {
      "horizon_steps": 19,
      "horizon_minutes": 570,
      "target_timestamp_utc": "2026-07-14T17:00:00Z",
      "hp30": 1.7752623558044434
    },
    {
      "horizon_steps": 20,
      "horizon_minutes": 600,
      "target_timestamp_utc": "2026-07-14T17:30:00Z",
      "hp30": 1.8700368404388428
    },
    {
      "horizon_steps": 21,
      "horizon_minutes": 630,
      "target_timestamp_utc": "2026-07-14T18:00:00Z",
      "hp30": 1.8514277935028076
    },
    {
      "horizon_steps": 22,
      "horizon_minutes": 660,
      "target_timestamp_utc": "2026-07-14T18:30:00Z",
      "hp30": 1.8450143337249756
    },
    {
      "horizon_steps": 23,
      "horizon_minutes": 690,
      "target_timestamp_utc": "2026-07-14T19:00:00Z",
      "hp30": 1.8290034532546997
    },
    {
      "horizon_steps": 24,
      "horizon_minutes": 720,
      "target_timestamp_utc": "2026-07-14T19:30:00Z",
      "hp30": 1.8490463495254517
    }
  ],
  "analysis": {
    "mcd": {
      "num_samples": 100,
      "n_std": 2.0,
      "mean": [
        1.6715539693832397,
        1.6458282470703125,
        1.7140405178070068,
        1.6279618740081787,
        1.7338168621063232,
        1.6914176940917969,
        1.717969536781311,
        1.6876870393753052,
        1.6891226768493652,
        1.7425018548965454,
        1.7459778785705566,
        1.7949098348617554,
        1.8099279403686523,
        1.8012994527816772,
        1.8359473943710327,
        1.7760183811187744,
        1.807680606842041,
        1.855851173400879,
        1.7504884004592896,
        1.8361320495605469,
        1.8191077709197998,
        1.8064903020858765,
        1.8049827814102173,
        1.807982325553894
      ],
      "std": [
        0.13593217730522156,
        0.11222612857818604,
        0.12058261036872864,
        0.10384665429592133,
        0.09487977623939514,
        0.09366852790117264,
        0.08661291748285294,
        0.08434198051691055,
        0.07379121333360672,
        0.09011723846197128,
        0.0738619938492775,
        0.06522493809461594,
        0.06889531016349792,
        0.08409979939460754,
        0.0699877068400383,
        0.08154232800006866,
        0.06328178942203522,
        0.06651514768600464,
        0.07267329841852188,
        0.08095914870500565,
        0.0635533332824707,
        0.079427070915699,
        0.08078932017087936,
        0.07859497517347336
      ],
      "lower": [
        1.3996896743774414,
        1.4213759899139404,
        1.4728753566741943,
        1.4202685356140137,
        1.5440573692321777,
        1.5040806531906128,
        1.5447436571121216,
        1.5190030336380005,
        1.541540265083313,
        1.5622674226760864,
        1.598253846168518,
        1.6644599437713623,
        1.6721372604370117,
        1.6330997943878174,
        1.695971965789795,
        1.6129337549209595,
        1.681117057800293,
        1.7228208780288696,
        1.6051417589187622,
        1.6742137670516968,
        1.6920011043548584,
        1.6476361751556396,
        1.6434041261672974,
        1.6507923603057861
      ],
      "upper": [
        1.943418264389038,
        1.8702805042266846,
        1.9552056789398193,
        1.8356552124023438,
        1.9235763549804688,
        1.878754734992981,
        1.8911954164505005,
        1.8563710451126099,
        1.8367050886154175,
        1.9227362871170044,
        1.8937019109725952,
        1.9253597259521484,
        1.947718620300293,
        1.969499111175537,
        1.9759228229522705,
        1.9391030073165894,
        1.934244155883789,
        1.9888814687728882,
        1.895835041999817,
        1.998050332069397,
        1.9462144374847412,
        1.9653444290161133,
        1.9665614366531372,
        1.965172290802002
      ]
    }
  },
  "history": [
    {
      "timestamp_utc": "2026-07-13T20:00:00Z",
      "hp30": 2.0
    },
    {
      "timestamp_utc": "2026-07-13T20:30:00Z",
      "hp30": 2.333
    },
    {
      "timestamp_utc": "2026-07-13T21:00:00Z",
      "hp30": 2.667
    },
    {
      "timestamp_utc": "2026-07-13T21:30:00Z",
      "hp30": 3.667
    },
    {
      "timestamp_utc": "2026-07-13T22:00:00Z",
      "hp30": 3.0
    },
    {
      "timestamp_utc": "2026-07-13T22:30:00Z",
      "hp30": 3.333
    },
    {
      "timestamp_utc": "2026-07-13T23:00:00Z",
      "hp30": 3.333
    },
    {
      "timestamp_utc": "2026-07-13T23:30:00Z",
      "hp30": 4.0
    },
    {
      "timestamp_utc": "2026-07-14T00:00:00Z",
      "hp30": 3.0
    },
    {
      "timestamp_utc": "2026-07-14T00:30:00Z",
      "hp30": 2.333
    },
    {
      "timestamp_utc": "2026-07-14T01:00:00Z",
      "hp30": 1.333
    },
    {
      "timestamp_utc": "2026-07-14T01:30:00Z",
      "hp30": 1.333
    },
    {
      "timestamp_utc": "2026-07-14T02:00:00Z",
      "hp30": 1.0
    },
    {
      "timestamp_utc": "2026-07-14T02:30:00Z",
      "hp30": 0.667
    },
    {
      "timestamp_utc": "2026-07-14T03:00:00Z",
      "hp30": 0.667
    },
    {
      "timestamp_utc": "2026-07-14T03:30:00Z",
      "hp30": 0.667
    },
    {
      "timestamp_utc": "2026-07-14T04:00:00Z",
      "hp30": 1.667
    },
    {
      "timestamp_utc": "2026-07-14T04:30:00Z",
      "hp30": 1.667
    },
    {
      "timestamp_utc": "2026-07-14T05:00:00Z",
      "hp30": 2.0
    },
    {
      "timestamp_utc": "2026-07-14T05:30:00Z",
      "hp30": 2.333
    },
    {
      "timestamp_utc": "2026-07-14T06:00:00Z",
      "hp30": 1.667
    },
    {
      "timestamp_utc": "2026-07-14T06:30:00Z",
      "hp30": 1.667
    },
    {
      "timestamp_utc": "2026-07-14T07:00:00Z",
      "hp30": 1.667
    },
    {
      "timestamp_utc": "2026-07-14T07:30:00Z",
      "hp30": 1.667
    }
  ]
}