{
  "run_timestamp_utc": "2026-07-23T21:01:38Z",
  "anchor_timestamp_utc": "2026-07-23T20:30:00Z",
  "model": {
    "profile": "in12h_out12h_gnn_patchtst",
    "checkpoint_path": "checkpoint/model_best.pth",
    "checkpoint_sha256": "6625c0b04d36",
    "val_loss_at_train": null,
    "val_mae_at_train": null,
    "val_rmse_at_train": null
  },
  "input": {
    "event_csv": "/home/runner/work/hp-prediction/hp-prediction/vendor/realtime-regression-sw/dataset/events/20260723203000.csv",
    "sources": {
      "noaa_plasma_url": "https://services.swpc.noaa.gov/json/rtsw/rtsw_wind_1m.json",
      "noaa_mag_url": "https://services.swpc.noaa.gov/json/rtsw/rtsw_mag_1m.json",
      "gfz_hpo_url": "https://www-app3.gfz-potsdam.de/kp_index/Hp30_ap30_nowcast.txt"
    },
    "missing_data_filled_fraction": 0.0
  },
  "forecast": [
    {
      "horizon_steps": 1,
      "horizon_minutes": 30,
      "target_timestamp_utc": "2026-07-23T21:00:00Z",
      "hp30": 1.1894094944000244
    },
    {
      "horizon_steps": 2,
      "horizon_minutes": 60,
      "target_timestamp_utc": "2026-07-23T21:30:00Z",
      "hp30": 1.2674198150634766
    },
    {
      "horizon_steps": 3,
      "horizon_minutes": 90,
      "target_timestamp_utc": "2026-07-23T22:00:00Z",
      "hp30": 1.2220107316970825
    },
    {
      "horizon_steps": 4,
      "horizon_minutes": 120,
      "target_timestamp_utc": "2026-07-23T22:30:00Z",
      "hp30": 1.1088557243347168
    },
    {
      "horizon_steps": 5,
      "horizon_minutes": 150,
      "target_timestamp_utc": "2026-07-23T23:00:00Z",
      "hp30": 1.3399145603179932
    },
    {
      "horizon_steps": 6,
      "horizon_minutes": 180,
      "target_timestamp_utc": "2026-07-23T23:30:00Z",
      "hp30": 1.2032175064086914
    },
    {
      "horizon_steps": 7,
      "horizon_minutes": 210,
      "target_timestamp_utc": "2026-07-24T00:00:00Z",
      "hp30": 1.2425270080566406
    },
    {
      "horizon_steps": 8,
      "horizon_minutes": 240,
      "target_timestamp_utc": "2026-07-24T00:30:00Z",
      "hp30": 1.2133647203445435
    },
    {
      "horizon_steps": 9,
      "horizon_minutes": 270,
      "target_timestamp_utc": "2026-07-24T01:00:00Z",
      "hp30": 1.231106162071228
    },
    {
      "horizon_steps": 10,
      "horizon_minutes": 300,
      "target_timestamp_utc": "2026-07-24T01:30:00Z",
      "hp30": 1.3613463640213013
    },
    {
      "horizon_steps": 11,
      "horizon_minutes": 330,
      "target_timestamp_utc": "2026-07-24T02:00:00Z",
      "hp30": 1.2320613861083984
    },
    {
      "horizon_steps": 12,
      "horizon_minutes": 360,
      "target_timestamp_utc": "2026-07-24T02:30:00Z",
      "hp30": 1.3870266675949097
    },
    {
      "horizon_steps": 13,
      "horizon_minutes": 390,
      "target_timestamp_utc": "2026-07-24T03:00:00Z",
      "hp30": 1.3311264514923096
    },
    {
      "horizon_steps": 14,
      "horizon_minutes": 420,
      "target_timestamp_utc": "2026-07-24T03:30:00Z",
      "hp30": 1.375150203704834
    },
    {
      "horizon_steps": 15,
      "horizon_minutes": 450,
      "target_timestamp_utc": "2026-07-24T04:00:00Z",
      "hp30": 1.4106333255767822
    },
    {
      "horizon_steps": 16,
      "horizon_minutes": 480,
      "target_timestamp_utc": "2026-07-24T04:30:00Z",
      "hp30": 1.4190723896026611
    },
    {
      "horizon_steps": 17,
      "horizon_minutes": 510,
      "target_timestamp_utc": "2026-07-24T05:00:00Z",
      "hp30": 1.3669075965881348
    },
    {
      "horizon_steps": 18,
      "horizon_minutes": 540,
      "target_timestamp_utc": "2026-07-24T05:30:00Z",
      "hp30": 1.3735896348953247
    },
    {
      "horizon_steps": 19,
      "horizon_minutes": 570,
      "target_timestamp_utc": "2026-07-24T06:00:00Z",
      "hp30": 1.3447548151016235
    },
    {
      "horizon_steps": 20,
      "horizon_minutes": 600,
      "target_timestamp_utc": "2026-07-24T06:30:00Z",
      "hp30": 1.331888198852539
    },
    {
      "horizon_steps": 21,
      "horizon_minutes": 630,
      "target_timestamp_utc": "2026-07-24T07:00:00Z",
      "hp30": 1.3638877868652344
    },
    {
      "horizon_steps": 22,
      "horizon_minutes": 660,
      "target_timestamp_utc": "2026-07-24T07:30:00Z",
      "hp30": 1.2275111675262451
    },
    {
      "horizon_steps": 23,
      "horizon_minutes": 690,
      "target_timestamp_utc": "2026-07-24T08:00:00Z",
      "hp30": 1.3423773050308228
    },
    {
      "horizon_steps": 24,
      "horizon_minutes": 720,
      "target_timestamp_utc": "2026-07-24T08:30:00Z",
      "hp30": 1.3923636674880981
    }
  ],
  "analysis": {
    "mcd": {
      "num_samples": 100,
      "n_std": 2.0,
      "mean": [
        1.2209150791168213,
        1.290766716003418,
        1.2447922229766846,
        1.1346514225006104,
        1.3488088846206665,
        1.2214444875717163,
        1.266139030456543,
        1.2425519227981567,
        1.249793529510498,
        1.3848921060562134,
        1.2667276859283447,
        1.4023480415344238,
        1.3447418212890625,
        1.3931834697723389,
        1.4199541807174683,
        1.447913646697998,
        1.3776147365570068,
        1.3904359340667725,
        1.371644139289856,
        1.3640799522399902,
        1.3869656324386597,
        1.2671068906784058,
        1.3722418546676636,
        1.410885214805603
      ],
      "std": [
        0.23816461861133575,
        0.20397016406059265,
        0.201482892036438,
        0.17372466623783112,
        0.14724935591220856,
        0.1555209457874298,
        0.163009375333786,
        0.16368159651756287,
        0.14242486655712128,
        0.15296782553195953,
        0.15244634449481964,
        0.15932218730449677,
        0.15568959712982178,
        0.1534399688243866,
        0.15606209635734558,
        0.15509434044361115,
        0.14213275909423828,
        0.15278644859790802,
        0.1643916517496109,
        0.1716095358133316,
        0.16276581585407257,
        0.13894356787204742,
        0.13009990751743317,
        0.13098858296871185
      ],
      "lower": [
        0.7445858716964722,
        0.8828263878822327,
        0.8418264389038086,
        0.7872021198272705,
        1.0543102025985718,
        0.9104025959968567,
        0.940120279788971,
        0.915188729763031,
        0.9649437665939331,
        1.0789564847946167,
        0.9618350267410278,
        1.083703637123108,
        1.033362627029419,
        1.086303472518921,
        1.1078300476074219,
        1.1377249956130981,
        1.0933492183685303,
        1.0848630666732788,
        1.0428608655929565,
        1.0208609104156494,
        1.061434030532837,
        0.9892197847366333,
        1.1120420694351196,
        1.148908019065857
      ],
      "upper": [
        1.6972442865371704,
        1.698707103729248,
        1.6477580070495605,
        1.4821007251739502,
        1.6433075666427612,
        1.5324864387512207,
        1.5921578407287598,
        1.5699150562286377,
        1.534643292427063,
        1.69082772731781,
        1.5716203451156616,
        1.7209924459457397,
        1.656121015548706,
        1.7000634670257568,
        1.7320783138275146,
        1.758102297782898,
        1.6618802547454834,
        1.6960088014602661,
        1.7004274129867554,
        1.707298994064331,
        1.7124972343444824,
        1.5449939966201782,
        1.6324416399002075,
        1.6728624105453491
      ]
    }
  },
  "history": [
    {
      "timestamp_utc": "2026-07-23T09:00:00Z",
      "hp30": 3.0
    },
    {
      "timestamp_utc": "2026-07-23T09:30:00Z",
      "hp30": 3.333
    },
    {
      "timestamp_utc": "2026-07-23T10:00:00Z",
      "hp30": 3.333
    },
    {
      "timestamp_utc": "2026-07-23T10:30:00Z",
      "hp30": 3.333
    },
    {
      "timestamp_utc": "2026-07-23T11:00:00Z",
      "hp30": 2.333
    },
    {
      "timestamp_utc": "2026-07-23T11:30:00Z",
      "hp30": 3.0
    },
    {
      "timestamp_utc": "2026-07-23T12:00:00Z",
      "hp30": 2.333
    },
    {
      "timestamp_utc": "2026-07-23T12:30:00Z",
      "hp30": 2.333
    },
    {
      "timestamp_utc": "2026-07-23T13:00:00Z",
      "hp30": 3.667
    },
    {
      "timestamp_utc": "2026-07-23T13:30:00Z",
      "hp30": 3.667
    },
    {
      "timestamp_utc": "2026-07-23T14:00:00Z",
      "hp30": 3.0
    },
    {
      "timestamp_utc": "2026-07-23T14:30:00Z",
      "hp30": 4.667
    },
    {
      "timestamp_utc": "2026-07-23T15:00:00Z",
      "hp30": 5.0
    },
    {
      "timestamp_utc": "2026-07-23T15:30:00Z",
      "hp30": 5.333
    },
    {
      "timestamp_utc": "2026-07-23T16:00:00Z",
      "hp30": 5.333
    },
    {
      "timestamp_utc": "2026-07-23T16:30:00Z",
      "hp30": 4.333
    },
    {
      "timestamp_utc": "2026-07-23T17:00:00Z",
      "hp30": 4.0
    },
    {
      "timestamp_utc": "2026-07-23T17:30:00Z",
      "hp30": 3.667
    },
    {
      "timestamp_utc": "2026-07-23T18:00:00Z",
      "hp30": 5.333
    },
    {
      "timestamp_utc": "2026-07-23T18:30:00Z",
      "hp30": 4.333
    },
    {
      "timestamp_utc": "2026-07-23T19:00:00Z",
      "hp30": 4.667
    },
    {
      "timestamp_utc": "2026-07-23T19:30:00Z",
      "hp30": 6.333
    },
    {
      "timestamp_utc": "2026-07-23T20:00:00Z",
      "hp30": 6.0
    },
    {
      "timestamp_utc": "2026-07-23T20:30:00Z",
      "hp30": 4.0
    }
  ]
}